iohclustering/__init__.py
iohclustering/cluster_base.py
iohclustering/cluster_baseline_problems.py
iohclustering/cluster_metrics.py
iohclustering/utils.py
iohclustering/utils_metrics.py
iohclustering/static/__init__.py
iohclustering/static/breast_pca.txt
iohclustering/static/diabetes_pca.txt
iohclustering/static/german_postal_selected.txt
iohclustering/static/glass_pca.txt
iohclustering/static/iris_pca.txt
iohclustering/static/kc1_pca.txt
iohclustering/static/kmeans_baseline_100.csv
iohclustering/static/mfeat-fourier_pca.txt
iohclustering/static/ruspini_selected.txt
iohclustering/static/segment_pca.txt
iohclustering/static/wine_pca.txt
iohclustering-0.0.3.dist-info/METADATA
iohclustering-0.0.3.dist-info/WHEEL
iohclustering-0.0.3.dist-info/top_level.txt
iohclustering-0.0.3.dist-info/RECORD
