Metadata-Version: 2.4
Name: iohclustering
Version: 0.0.3
Summary: Package for IOH Clustering problems
Classifier: Programming Language :: Python :: 3
Classifier: License :: OSI Approved :: MIT License
Classifier: Operating System :: OS Independent
Requires-Python: >=3.10
Requires-Dist: ioh
Requires-Dist: numpy
Requires-Dist: pandas
Provides-Extra: test
Requires-Dist: coverage; extra == "test"
